{
    "1": {
        "title": "Exodus: Gods and Kings",
        "url": "https://en.wikipedia.org/wiki/Exodus%3A%20Gods%20and%20Kings",
        "year": "2014",
        "poster": "https://upload.wikimedia.org/wikipedia/en/thumb/c/cd/Exodus2014Poster.jpg/220px-Exodus2014Poster.jpg",
        "actors": [
            "Christian Bale",
            "Joel Edgerton",
            "John Turturro",
            "Aaron Paul",
            "Ben Mendelsohn",
            "Sigourney Weaver",
            "Ben Kingsley"
        ],
        "actors_urls": [
            "https://en.wikipedia.org/wiki/Christian_Bale",
            "https://en.wikipedia.org/wiki/Joel_Edgerton",
            "https://en.wikipedia.org/wiki/John_Turturro",
            "https://en.wikipedia.org/wiki/Aaron_Paul",
            "https://en.wikipedia.org/wiki/Ben_Mendelsohn",
            "https://en.wikipedia.org/wiki/Sigourney_Weaver",
            "https://en.wikipedia.org/wiki/Ben_Kingsley"
        ]
    },
    "2": {
        "title": "The Little Mermaid (2023 film)",
        "url": "https://en.wikipedia.org/wiki/The%20Little%20Mermaid%20%282023%20film%29",
        "year": "2023",
        "poster": "https://upload.wikimedia.org/wikipedia/en/thumb/f/f4/The_Little_Mermaid_%282023_film%29.png/220px-The_Little_Mermaid_%282023_film%29.png",
        "actors": [
            "Halle Bailey",
            "Daveed Diggs",
            "Jacob Tremblay",
            "Awkwafina",
            "Jonah Hauer-King",
            "Art Malik",
            "Noma Dumezweni",
            "Javier Bardem",
            "Melissa McCarthy"
        ],
        "actors_urls": [
            "https://en.wikipedia.org/wiki/Halle_Bailey",
            "https://en.wikipedia.org/wiki/Daveed_Diggs",
            "https://en.wikipedia.org/wiki/Jacob_Tremblay",
            "https://en.wikipedia.org/wiki/Awkwafina",
            "https://en.wikipedia.org/wiki/Jonah_Hauer-King",
            "https://en.wikipedia.org/wiki/Art_Malik",
            "https://en.wikipedia.org/wiki/Noma_Dumezweni",
            "https://en.wikipedia.org/wiki/Javier_Bardem",
            "https://en.wikipedia.org/wiki/Melissa_McCarthy"
        ]
    },
    "3": {
        "title": "Ghost in the Shell (2017 film)",
        "url": "https://en.wikipedia.org/wiki/Ghost%20in%20the%20Shell%20%282017%20film%29",
        "year": "2017",
        "poster": "https://upload.wikimedia.org/wikipedia/en/thumb/1/11/Ghost_in_the_Shell_%282017_film%29.png/220px-Ghost_in_the_Shell_%282017_film%29.png",
        "actors": [
            "Scarlett Johansson",
            "Takeshi Kitano",
            "Michael Pitt",
            "Pilou Asbæk",
            "Chin Han (actor, born 1969)",
            "Juliette Binoche"
        ],
        "actors_urls": [
            "https://en.wikipedia.org/wiki/Scarlett_Johansson",
            "https://en.wikipedia.org/wiki/Takeshi_Kitano",
            "https://en.wikipedia.org/wiki/Michael_Pitt",
            "https://en.wikipedia.org/wiki/Pilou_Asb%C3%A6k",
            "https://en.wikipedia.org/wiki/Chin_Han_(actor,_born_1969)",
            "https://en.wikipedia.org/wiki/Juliette_Binoche"
        ]
    },
    "4": {
        "title": "Aloha (2015 film)",
        "url": "https://en.wikipedia.org/wiki/Aloha%20%282015%20film%29",
        "year": "2015",
        "poster": "https://upload.wikimedia.org/wikipedia/en/thumb/7/73/Aloha_poster.jpg/220px-Aloha_poster.jpg",
        "actors": [
            "Bradley Cooper",
            "Emma Stone",
            "Rachel McAdams",
            "Bill Murray",
            "John Krasinski",
            "Danny McBride",
            "Alec Baldwin"
        ],
        "actors_urls": [
            "https://en.wikipedia.org/wiki/Bradley_Cooper",
            "https://en.wikipedia.org/wiki/Emma_Stone",
            "https://en.wikipedia.org/wiki/Rachel_McAdams",
            "https://en.wikipedia.org/wiki/Bill_Murray",
            "https://en.wikipedia.org/wiki/John_Krasinski",
            "https://en.wikipedia.org/wiki/Danny_McBride",
            "https://en.wikipedia.org/wiki/Alec_Baldwin"
        ]
    },
    "5": {
        "title": "Stonewall (2015 film)",
        "url": "https://en.wikipedia.org/wiki/Stonewall%20%282015%20film%29",
        "year": "2015",
        "poster": "https://upload.wikimedia.org/wikipedia/en/thumb/3/37/Stonewall_%282015_film%29_poster.jpg/220px-Stonewall_%282015_film%29_poster.jpg",
        "actors": [
            "Jeremy Irvine",
            "Jonny Beauchamp",
            "Joey King",
            "Caleb Landry Jones",
            "Matt Craven",
            "Jonathan Rhys Meyers",
            "Ron Perlman"
        ],
        "actors_urls": [
            "https://en.wikipedia.org/wiki/Jeremy_Irvine",
            "",
            "https://en.wikipedia.org/wiki/Joey_King",
            "https://en.wikipedia.org/wiki/Caleb_Landry_Jones",
            "https://en.wikipedia.org/wiki/Matt_Craven",
            "https://en.wikipedia.org/wiki/Jonathan_Rhys_Meyers",
            "https://en.wikipedia.org/wiki/Ron_Perlman"
        ]
    },
    "6": {
        "title": "Gods of Egypt (film)",
        "url": "https://en.wikipedia.org/wiki/Gods%20of%20Egypt%20%28film%29",
        "year": "2016",
        "poster": "https://upload.wikimedia.org/wikipedia/en/thumb/2/2f/Gods_of_Egypt_poster.jpg/220px-Gods_of_Egypt_poster.jpg",
        "actors": [
            "Nikolaj Coster-Waldau",
            "Brenton Thwaites",
            "Chadwick Boseman",
            "Élodie Yung",
            "Courtney Eaton",
            "Rufus Sewell",
            "Gerard Butler",
            "Geoffrey Rush"
        ],
        "actors_urls": [
            "https://en.wikipedia.org/wiki/Nikolaj_Coster-Waldau",
            "https://en.wikipedia.org/wiki/Brenton_Thwaites",
            "https://en.wikipedia.org/wiki/Chadwick_Boseman",
            "https://en.wikipedia.org/wiki/%C3%89lodie_Yung",
            "https://en.wikipedia.org/wiki/Courtney_Eaton",
            "https://en.wikipedia.org/wiki/Rufus_Sewell",
            "https://en.wikipedia.org/wiki/Gerard_Butler",
            "https://en.wikipedia.org/wiki/Geoffrey_Rush"
        ]
    }
}